{
  "project_info": {
    "project_number": "880215740712",
    "firebase_url": "https://qzyapp-de0e0.firebaseio.com",
    "project_id": "qzyapp-de0e0",
    "storage_bucket": "qzyapp-de0e0.appspot.com"
  },
  "client": [
    {
      "client_info": {
        "mobilesdk_app_id": "1:880215740712:android:e3d3cf1f185e792303001d",
        "android_client_info": {
          "package_name": "com.qyz.malls"
        }
      },
      "oauth_client": [
        {
          "client_id": "880215740712-4ductschgljt9vb4talgi3tukuiq56bh.apps.googleusercontent.com",
          "client_type": 1,
          "android_info": {
            "package_name": "com.qyz.malls",
            "certificate_hash": "a0b6a3e78f7cfd2551b3c83df8947f2364677c96"
          }
        },
        {
          "client_id": "880215740712-4tgoek1473enuta4dh1cnovcdpthtcp9.apps.googleusercontent.com",
          "client_type": 3
        }
      ],
      "api_key": [
        {
          "current_key": "AIzaSyBydi_fa15g7E6Zy0Ki06cTnIosSOL5FkE"
        }
      ],
      "services": {
        "appinvite_service": {
          "other_platform_oauth_client": [
            {
              "client_id": "880215740712-4tgoek1473enuta4dh1cnovcdpthtcp9.apps.googleusercontent.com",
              "client_type": 3
            }
          ]
        }
      }
    }
  ],
  "configuration_version": "1"
}